cloudglue/__init__.py
cloudglue/_version.py
cloudglue/client/__init__.py
cloudglue/client/main.py
cloudglue/client/resources/__init__.py
cloudglue/client/resources/base.py
cloudglue/client/resources/chat.py
cloudglue/client/resources/collections.py
cloudglue/client/resources/describe.py
cloudglue/client/resources/extract.py
cloudglue/client/resources/face_detection.py
cloudglue/client/resources/face_match.py
cloudglue/client/resources/file_segments.py
cloudglue/client/resources/files.py
cloudglue/client/resources/frames.py
cloudglue/client/resources/responses.py
cloudglue/client/resources/search.py
cloudglue/client/resources/segmentations.py
cloudglue/client/resources/segments.py
cloudglue/client/resources/share.py
cloudglue/client/resources/tags.py
cloudglue/client/resources/thumbnails.py
cloudglue/client/resources/transcribe.py
cloudglue/sdk/__init__.py
cloudglue/sdk/api_client.py
cloudglue/sdk/api_response.py
cloudglue/sdk/configuration.py
cloudglue/sdk/exceptions.py
cloudglue/sdk/py.typed
cloudglue/sdk/rest.py
cloudglue/sdk/api/__init__.py
cloudglue/sdk/api/chat_api.py
cloudglue/sdk/api/collections_api.py
cloudglue/sdk/api/describe_api.py
cloudglue/sdk/api/extract_api.py
cloudglue/sdk/api/face_detection_api.py
cloudglue/sdk/api/face_match_api.py
cloudglue/sdk/api/file_segments_api.py
cloudglue/sdk/api/files_api.py
cloudglue/sdk/api/frames_api.py
cloudglue/sdk/api/response_api.py
cloudglue/sdk/api/search_api.py
cloudglue/sdk/api/segmentations_api.py
cloudglue/sdk/api/segments_api.py
cloudglue/sdk/api/share_api.py
cloudglue/sdk/api/tags_api.py
cloudglue/sdk/api/thumbnails_api.py
cloudglue/sdk/api/transcribe_api.py
cloudglue/sdk/api/webhooks_api.py
cloudglue/sdk/models/__init__.py
cloudglue/sdk/models/add_collection_file.py
cloudglue/sdk/models/add_you_tube_collection_file.py
cloudglue/sdk/models/chapter.py
cloudglue/sdk/models/chat_completion_list.py
cloudglue/sdk/models/chat_completion_list_data_inner.py
cloudglue-0.5.3.dist-info/licenses/LICENSE.md
cloudglue-0.5.3.dist-info/METADATA
cloudglue-0.5.3.dist-info/WHEEL
cloudglue-0.5.3.dist-info/top_level.txt
cloudglue-0.5.3.dist-info/RECORD
