Metadata-Version: 2.4
Name: cloudglue
Version: 0.5.3
Summary: Python SDK for Cloudglue API
Author-email: "Aviary Inc." <hello@aviaryhq.com>
License: Apache-2.0
Project-URL: Homepage, https://github.com/aviaryhq/cloudglue-python
Project-URL: Bug Tracker, https://github.com/aviaryhq/cloudglue-python/issues
Keywords: cloudglue,api,sdk
Classifier: Development Status :: 3 - Alpha
Classifier: Intended Audience :: Developers
Classifier: Programming Language :: Python :: 3
Classifier: Programming Language :: Python :: 3.10
Classifier: Programming Language :: Python :: 3.11
Classifier: Programming Language :: Python :: 3.12
Classifier: Operating System :: OS Independent
Requires-Python: >=3.10
License-File: LICENSE.md
Requires-Dist: urllib3>=2.2.3
Requires-Dist: python-dateutil
Requires-Dist: requests>=2.32.2
Requires-Dist: certifi>=2024.12.14
Requires-Dist: pydantic>=2.10.6
Dynamic: license-file
